geedl/__init__.py
geedl/__version__.py
geedl/gee/__init__.py
geedl/gee/data_loader.py
geedl/gee/data_processing.py
geedl/gee/gee_utils.py
geedl/gee/notebook_utils.py
geedl/gee/para.py
geedl/gee/plotter.py
geedl-0.1.6.dist-info/METADATA
geedl-0.1.6.dist-info/WHEEL
geedl-0.1.6.dist-info/top_level.txt
geedl-0.1.6.dist-info/RECORD
