Metadata-Version: 2.1
Name: geedl
Version: 0.1.6
Summary: A Python package for Google Earth Engine tools
Home-page: https://github.com/gg-zl/GEE_py
Author: Zhang Lei
Author-email: zhanglei1136@163.com
Classifier: Programming Language :: Python :: 3
Classifier: License :: OSI Approved :: MIT License
Classifier: Operating System :: OS Independent
Requires-Python: >=3.7
Requires-Dist: numpy
Requires-Dist: earthengine-api
Requires-Dist: geemap
Requires-Dist: pandas
Requires-Dist: matplotlib
